clip_streamlit/__init__.py
clip_streamlit/app.py
clip_streamlit/base.py
clip_streamlit/version.py
clip_streamlit/__pycache__/__init__.cpython-312.pyc
clip_streamlit/__pycache__/app.cpython-312.pyc
clip_streamlit/__pycache__/version.cpython-312.pyc
clip_streamlit-0.1.1.dist-info/licenses/LICENSE
clip_streamlit-0.1.1.dist-info/METADATA
clip_streamlit-0.1.1.dist-info/WHEEL
clip_streamlit-0.1.1.dist-info/entry_points.txt
clip_streamlit-0.1.1.dist-info/top_level.txt
clip_streamlit-0.1.1.dist-info/RECORD
