Metadata-Version: 2.4
Name: clip-streamlit
Version: 0.1.1
Summary: Zero-shot image classification using CLIP and Streamlit
Home-page: https://github.com/fake-babu/clip-streamlit
Author: fake-babu
Author-email: fake-babu <apunfakebabu@gmail.com>
License: MIT
Project-URL: Homepage, https://github.com/fake-babu/clip-streamlit
Project-URL: Repository, https://github.com/fake-babu/clip-streamlit.git
Classifier: Development Status :: 3 - Alpha
Classifier: Intended Audience :: Developers
Classifier: Topic :: Scientific/Engineering :: Artificial Intelligence
Classifier: License :: OSI Approved :: MIT License
Classifier: Programming Language :: Python :: 3
Classifier: Programming Language :: Python :: 3.7
Classifier: Programming Language :: Python :: 3.8
Classifier: Programming Language :: Python :: 3.9
Requires-Python: >=3.7
License-File: LICENSE
Requires-Dist: streamlit>=1.0.0
Requires-Dist: torch>=1.7.0
Requires-Dist: Pillow>=8.0.0
Dynamic: author
Dynamic: home-page
Dynamic: license-file
Dynamic: requires-python
